wradlib_data/__init__.py
wradlib_data/dataset.py
wradlib_data/registry.txt
wradlib_data/version.py
wradlib_data/tests/test_dataset.py
wradlib_data-0.12.0.dist-info/LICENSE
wradlib_data-0.12.0.dist-info/METADATA
wradlib_data-0.12.0.dist-info/WHEEL
wradlib_data-0.12.0.dist-info/top_level.txt
wradlib_data-0.12.0.dist-info/RECORD
