Metadata-Version: 2.2
Name: wradlib-data
Version: 0.12.0
Summary: Provides utility functions for accessing data repository for wradlib examples/notebooks
Maintainer-email: wradlib developers <wradlib@wradlib.org>
License: MIT License
Project-URL: homepage, https://wradlib.org
Project-URL: documentation, https://docs.wradlib.org/
Project-URL: repository, https://github.com/wradlib/wradlib-data
Classifier: Development Status :: 5 - Production/Stable
Classifier: License :: OSI Approved :: MIT License
Classifier: Natural Language :: English
Classifier: Programming Language :: Python :: 3
Classifier: Programming Language :: Python :: 3.9
Classifier: Programming Language :: Python :: 3.10
Classifier: Programming Language :: Python :: 3.11
Classifier: Topic :: Scientific/Engineering
Classifier: Operating System :: OS Independent
Classifier: Intended Audience :: Science/Research
Requires-Python: >=3.9
License-File: LICENSE
Requires-Dist: pooch
